{"contentAdvisoryRating": "4+", "features": [], "languageCodesISO2A": ["EN"], "ipadScreenshotUrls": [], "releaseDate": "2009-11-03T21:52:07Z", "currency": "USD", "artistId": 336861342, "userRatingCountForCurrentVersion": 19, "wrapperType": "software", "advisories": [], "genres": ["Lifestyle"], "trackId": 336861339, "description": "Shopping bebe on the go has never been so easy. Browse the full fashion collection, easily zoom for details and enjoy secure, super-fast checkout. Shopping in-store? Try bebe\u2019s store locator and inventory look-up features to find what you want, right where you are. You can even scan items for customer reviews and get exclusive in-app offers!", "artistName": "bebe Stores, inc.", "artworkUrl512": "http://a786.phobos.apple.com/us/r30/Purple5/v4/94/b1/d3/94b1d3ad-5b17-f2aa-4165-05d5769acef0/mzl.onjppncd.png", "version": "3.8", "primaryGenreId": 6012, "primaryGenreName": "Lifestyle", "fileSizeBytes": "6747860", "price": 0.0, "isGameCenterEnabled": false, "trackCensoredName": "bebe Mobile", "genreIds": ["6012"], "trackName": "bebe Mobile", "releaseNotes": "- Speed enhancements \n- Bug fixes", "sellerUrl": "http://www.bebe.com/", "screenshotUrls": ["http://a2.mzstatic.com/us/r30/Purple3/v4/5a/8e/d2/5a8ed28e-b9a7-670b-2c4c-838d3aedd414/screen1136x1136.jpeg", "http://a3.mzstatic.com/us/r30/Purple5/v4/79/a2/14/79a214c7-f6d9-8fa3-f1e4-0f0eccf0131d/screen1136x1136.jpeg", "http://a1.mzstatic.com/us/r30/Purple4/v4/0c/6b/e7/0c6be7b3-5da5-2a50-1081-7ebaa023b422/screen1136x1136.jpeg", "http://a2.mzstatic.com/us/r30/Purple4/v4/4c/de/f3/4cdef324-8379-8c15-3d62-42679f98962a/screen1136x1136.jpeg", "http://a4.mzstatic.com/us/r30/Purple5/v4/02/4b/d4/024bd461-b7ee-9f30-c877-3d085f7dbd24/screen1136x1136.jpeg"], "userRatingCount": 1956, "trackContentRating": "4+", "formattedPrice": "Free", "artistViewUrl": "https://itunes.apple.com/us/artist/bebe-stores-inc./id336861342?uo=4", "kind": "software", "averageUserRatingForCurrentVersion": 5.0, "sellerName": "bebe Stores, inc.", "supportedDevices": ["iPadMini", "iPadMini4G", "iPadFourthGen", "iPhone5s", "iPhone4", "iPad23G", "iPad2Wifi", "iPhone4S", "iPhone5", "iPadFourthGen4G", "iPadThirdGen4G", "iPadThirdGen", "iPodTouchFifthGen", "iPhone5c"], "artworkUrl100": "http://a786.phobos.apple.com/us/r30/Purple5/v4/94/b1/d3/94b1d3ad-5b17-f2aa-4165-05d5769acef0/mzl.onjppncd.png", "bundleId": "com.bebe.iPhoneApp", "trackViewUrl": "https://itunes.apple.com/us/app/bebe-mobile/id336861339?mt=8&uo=4", "minimumOsVersion": "7.0", "artworkUrl60": "http://a1141.phobos.apple.com/us/r30/Purple4/v4/30/60/30/30603092-e43b-b34d-fdad-bd16aea011d4/Icon.png", "averageUserRating": 3.5}