{"contentAdvisoryRating": "12+", "features": ["iosUniversal"], "languageCodesISO2A": ["EN", "FR", "DE", "IT", "ES"], "ipadScreenshotUrls": ["http://a4.mzstatic.com/us/r30/Purple5/v4/98/b7/77/98b77777-d07f-2c42-17bf-807c39f48d92/screen480x480.jpeg", "http://a1.mzstatic.com/us/r30/Purple3/v4/ce/8c/59/ce8c59e9-f081-3243-7d00-0d0f589b598d/screen480x480.jpeg", "http://a4.mzstatic.com/us/r30/Purple1/v4/00/66/c2/0066c26a-a4cb-b182-8a89-ab6a12264da3/screen480x480.jpeg", "http://a4.mzstatic.com/us/r30/Purple3/v4/a7/62/34/a762342e-5d99-aedd-cb30-bf0a52552277/screen480x480.jpeg", "http://a3.mzstatic.com/us/r30/Purple3/v4/86/b7/36/86b736db-32e0-3726-4cf1-ad8babf18600/screen480x480.jpeg"], "releaseDate": "2010-12-15T08:00:00Z", "currency": "USD", "artistId": 690289052, "userRatingCountForCurrentVersion": 32, "wrapperType": "software", "advisories": ["Infrequent/Mild Alcohol, Tobacco, or Drug Use or References"], "genres": ["Travel"], "trackId": 407690035, "description": "HotelTonight - Plan Less. Live More.\n\nHand-selected hotels at great prices. Book your Tonight, now up to 7 days in advance.\n\n*We are the night out with friends that turned into a road trip to Vegas\n*We are the birthday getaway you spontaneously booked for this weekend\n*We are the business trip you locked down in 10 seconds, at your soon-to-be-favorite hotel\n*We are the excuse to break out of your rut \n*We are HotelTonight. And we want you to plan a little less. And live a little more\n\nHere\u2019s how we deliver:\n\n*Great prices! Hotels give us last-minute discounts on their empty rooms. You get the very best rates, guaranteed \n*Book a room in just 10 seconds \u2013 3 taps and a swipe!\n*Hand-picked selection of top-rated hotels \u2013 we\u2019ve done the work to narrow down the best options\n*Themed \u201cPlaylists\" of hotels with recommendations on when and where to book (like hotels with great pools for Sunday Funday)\n*Categories (like Basic, Hip and Luxe) to make it easy to find the right hotel\n*Hotel descriptions that boil down the top 3 reasons why we like the hotels we work with \u2013 and why you will, too\n*Upcoming weather forecasts to help you decide where to stay and what to pack (besides your rubber ducky)\n*24/7 customer support (with real, live, nice people) \n*Say the magic word (\u201cBEYONCE\u201d) at the front desk and the concierge will break out into some killer Bob Fosse-style \u201cSingle Ladies\u201d moves (we wish)\n\nLet\u2019s connect:\n\n* Email: feedback@hoteltonight.com\n* Facebook: facebook.com/HotelTonight\n* Twitter: @HotelTonight\n* Instagram: @HotelTonight\n* Snapchat: @HotelTonight", "artistName": "Hotel Tonight Inc", "artworkUrl512": "http://a1248.phobos.apple.com/us/r30/Purple1/v4/ce/cc/1c/cecc1c03-1ae8-7985-b29f-871801affcc1/mzl.vscrgqbd.png", "version": "6.2", "primaryGenreId": 6003, "primaryGenreName": "Travel", "fileSizeBytes": "22818516", "price": 0.0, "isGameCenterEnabled": false, "trackCensoredName": "Hotel Tonight", "genreIds": ["6003"], "trackName": "Hotel Tonight", "releaseNotes": "*Tweaked some stuff to make the app even easier to use\n*Optimizations for Apple Pay\n*Watched the Giants' Victory Parade from our office. It was awesome. Confetti cannons!", "sellerUrl": "http://www.hoteltonight.com", "screenshotUrls": ["http://a4.mzstatic.com/us/r30/Purple1/v4/9a/1c/a0/9a1ca02a-52d4-c3eb-d402-49981c835df2/screen1136x1136.jpeg", "http://a5.mzstatic.com/us/r30/Purple5/v4/0f/9d/04/0f9d044c-0552-b176-03b5-701ee8f65aa3/screen1136x1136.jpeg", "http://a3.mzstatic.com/us/r30/Purple3/v4/84/ae/07/84ae07f1-845e-ce2d-2033-2328e197d1bc/screen1136x1136.jpeg", "http://a4.mzstatic.com/us/r30/Purple3/v4/5d/1d/a2/5d1da256-37a8-abad-b00c-ad9e7d3f0f2c/screen1136x1136.jpeg", "http://a3.mzstatic.com/us/r30/Purple3/v4/a0/76/03/a07603b5-1ab5-5b23-452d-ba20a0240efc/screen1136x1136.jpeg"], "userRatingCount": 11041, "trackContentRating": "12+", "formattedPrice": "Free", "artistViewUrl": "https://itunes.apple.com/us/artist/hotel-tonight-inc/id690289052?uo=4", "kind": "software", "averageUserRatingForCurrentVersion": 4.0, "sellerName": "Hotel Tonight Inc", "supportedDevices": ["iPadThirdGen4G", "iPadMini", "iPadMini4G", "iPhone5", "iPadFourthGen", "iPodTouchFifthGen", "iPhone5s", "iPhone5c", "iPadFourthGen4G", "iPhone4", "iPad2Wifi", "iPad23G", "iPadThirdGen", "iPhone4S"], "artworkUrl100": "http://a1248.phobos.apple.com/us/r30/Purple1/v4/ce/cc/1c/cecc1c03-1ae8-7985-b29f-871801affcc1/mzl.vscrgqbd.png", "bundleId": "com.hoteltonight.prod", "trackViewUrl": "https://itunes.apple.com/us/app/hotel-tonight/id407690035?mt=8&uo=4", "minimumOsVersion": "7.0", "artworkUrl60": "http://a656.phobos.apple.com/us/r30/Purple5/v4/3b/67/84/3b678418-a0b7-48b8-de03-bb12fc6d1eef/AppIcon60x60_U00402x.png", "averageUserRating": 4.5}