{"contentAdvisoryRating": "4+", "features": ["iosUniversal"], "languageCodesISO2A": ["AR", "EN", "FR", "DE", "IT", "JA", "KO", "PT", "RU", "ZH", "ES", "SV", "ZH", "TR"], "ipadScreenshotUrls": ["http://a2.mzstatic.com/us/r30/Purple1/v4/96/81/d4/9681d410-8f68-a1f4-f185-2294752e7bff/screen480x480.jpeg", "http://a1.mzstatic.com/us/r30/Purple3/v4/9f/20/6d/9f206d4c-d20a-c9c6-7831-d837054ca4ee/screen480x480.jpeg", "http://a2.mzstatic.com/us/r30/Purple3/v4/cc/f8/ad/ccf8adfd-acda-cd45-52b4-fa2993cdc289/screen480x480.jpeg", "http://a1.mzstatic.com/us/r30/Purple3/v4/d6/16/e1/d616e102-1fca-849b-e016-35b707d0b1c3/screen480x480.jpeg", "http://a4.mzstatic.com/us/r30/Purple3/v4/7c/77/8c/7c778c8b-03a3-7e2e-3fea-d73729e3b4a2/screen480x480.jpeg"], "releaseDate": "2011-04-19T23:06:12Z", "currency": "USD", "artistId": 319295335, "userRatingCountForCurrentVersion": 32, "wrapperType": "software", "advisories": [], "genres": ["Music", "Entertainment"], "trackId": 418987775, "description": "Listen to the world\u2019s largest collection of sports, news, music and talk radio. \n\nTuneIn has over 100,000 real radio stations and more than four million podcasts from all over the world. Discover, follow and listen to what\u2019s most important to you on your iPhone, iPad or iPod, all for free. This is real radio.\n\nWith TuneIn:\n-Listen to over 100,000 real radio stations from around the world, including sports, news, talk and music.\n-See what\u2019s playing live on your personalized home feed.\n-Find and follow your favorite stations, shows and podcasts to see their updates in your feed.\n\nFollow college sports on TuneIn with live play-by-play coverage from 85 Division 1 teams. Listen to the remainder\u200b\u200b of \u200bthe \u200bfootball season leading up to the playoffs with coverage of \u200btop-ranked \u200bAlabama, Oregon, Auburn, Florida State and more. College basketball is also \u200bunderway, and you can listen to teams like \u200bKentucky, \u200bArizona, \u200bWisconsin and \u200bDuke\u200b right on your smartphone or tablet. Listen on TuneIn and turn the game up!\n\nWant more from TuneIn?\nLike us on Facebook: facebook.com/tunein\nFollow us on Twitter: twitter.com/tunein\nFind us on Tumblr: blog.tunein.com\n\n\n\n\nThis software uses code of FFmpeg (ffmpeg.org) and LibMMS (Launchpad.net/libmms) licensed under the LGPLv2.1 (www.gnu.org/licenses/old-licenses/lgpl-2.1.html) and their source can be downloaded at tunein.com/mobile/ios.", "artistName": "TuneIn", "artworkUrl512": "http://a338.phobos.apple.com/us/r30/Purple5/v4/a1/34/d5/a134d5f4-2e46-ed8e-e226-7134c7bde268/mzl.bguhearq.png", "version": "6.8", "primaryGenreId": 6011, "primaryGenreName": "Music", "fileSizeBytes": "24513738", "price": 0.0, "isGameCenterEnabled": false, "trackCensoredName": "TuneIn Radio - Stream free music, sports, talk & news stations, podcasts, songs & tracks", "genreIds": ["6011", "6016"], "trackName": "TuneIn Radio - Stream free music, sports, talk & news stations, podcasts, songs & tracks", "releaseNotes": "-Google Chromecast compatibility so you can stream to your TV\n-Improvements to echo conversations\n-iPad design enhancements\n-VoiceOver improvements for visually impaired listeners\n-Supports iOS Handoff so you can switch seamlessly between your devices\n-Various bug fixes", "sellerUrl": "http://tunein.com/get-tunein/", "screenshotUrls": ["http://a3.mzstatic.com/us/r30/Purple3/v4/25/4c/e1/254ce154-7b27-db11-2107-ac5b2835c2a2/screen1136x1136.jpeg", "http://a4.mzstatic.com/us/r30/Purple3/v4/62/66/58/6266580f-e17a-86c5-c0d9-80caceddeaec/screen1136x1136.jpeg", "http://a5.mzstatic.com/us/r30/Purple3/v4/31/07/a6/3107a6d1-3e6b-701b-3bd5-fe85ca758e9a/screen1136x1136.jpeg", "http://a4.mzstatic.com/us/r30/Purple5/v4/75/14/bb/7514bb86-c74c-5c58-515e-855f745f7681/screen1136x1136.jpeg", "http://a4.mzstatic.com/us/r30/Purple1/v4/4a/a3/42/4aa34209-9021-4155-b82a-ae2f31a6e215/screen1136x1136.jpeg"], "userRatingCount": 76182, "trackContentRating": "4+", "formattedPrice": "Free", "artistViewUrl": "https://itunes.apple.com/us/artist/tunein/id319295335?uo=4", "kind": "software", "averageUserRatingForCurrentVersion": 4.0, "sellerName": "TuneIn", "supportedDevices": ["iPadFourthGen4G", "iPadFourthGen", "iPadThirdGen", "iPhone5c", "iPadThirdGen4G", "iPadMini4G", "iPhone5", "iPhone4S", "iPadMini", "iPhone5s", "iPhone4", "iPad23G", "iPad2Wifi", "iPodTouchFifthGen"], "artworkUrl100": "http://a338.phobos.apple.com/us/r30/Purple5/v4/a1/34/d5/a134d5f4-2e46-ed8e-e226-7134c7bde268/mzl.bguhearq.png", "bundleId": "com.tunein.TuneInRadio", "trackViewUrl": "https://itunes.apple.com/us/app/tunein-radio-stream-free-music/id418987775?mt=8&uo=4", "minimumOsVersion": "7.0", "artworkUrl60": "http://a1556.phobos.apple.com/us/r30/Purple3/v4/21/62/28/21622819-8373-a9d1-4792-87f807443964/AppIcon57x57.png", "averageUserRating": 4.5}