{"contentAdvisoryRating": "4+", "features": ["iosUniversal", "newsstand"], "languageCodesISO2A": ["NL", "EN", "FR", "DE", "PT", "ZH", "ZH"], "ipadScreenshotUrls": ["http://a3.mzstatic.com/us/r30/Purple/v4/f9/4c/db/f94cdb69-21c0-12fb-da6e-29d8869bb76f/screen480x480.jpeg", "http://a4.mzstatic.com/us/r30/Purple/v4/79/95/49/7995494a-2640-af76-8800-e511bdf51089/screen480x480.jpeg", "http://a4.mzstatic.com/us/r30/Purple/v4/dd/ee/7c/ddee7cd2-5c09-8c86-977f-90aba6c9a83e/screen480x480.jpeg", "http://a5.mzstatic.com/us/r30/Purple/v4/55/28/68/552868f0-7631-ee13-b75d-04be0acc9032/screen480x480.jpeg", "http://a5.mzstatic.com/us/r30/Purple/v4/88/dc/64/88dc64c6-4886-16da-7701-079dc94a7e3e/screen480x480.jpeg"], "releaseDate": "2011-10-13T01:13:01Z", "currency": "USD", "artistId": 386316599, "userRatingCountForCurrentVersion": 4, "wrapperType": "software", "advisories": [], "genres": ["Business", "Newsstand", "Professional & Trade"], "trackId": 464805176, "description": "**App Store Rewind 2011: Magic Numbers Newsstand App of the year in Germany, Austria and Switzerland**\nOur October 2012 issue is now FREE for all magic numbers users!\n\nMagic Numbers is a global magazine that brings all the worldwide trends and market research results on what really affects us as human-beings living in society. \n\nWhether it\u2019s about people\u2019s habits, customs, and behaviors, or opinions on international politics, products, brands and new technology, you will always find something interesting to read, no matter what your area of business is. You can be sure that you will find, inside every issue of Magic Numbers, useful and interesting facts about what is going on in the world today.\nThis highly interactive publication is as easy to navigate as it is to read. Graphics are clear and concise and are accompanied by exhaustive articles, which makes it extremely enjoyable.  \nBy downloading the app, you will have the option to have access the current issue as well as the option to purchase all of our back issues!\n\n\nMagic Numbers gives an in-depth exploration of the three following subjects on a global scale: \n\u2022 Politics, sports and society; up-to-date articles about the events that influence the world and our lives. \n\u2022 Products, brands and preferences; unveil what are the secrets to the success of a brand and what makes it thrive.\n\u2022 Lifestyle, personal habits and customs; discover what unites us as a community and learn about customs from all over the world. \n\n\nAbout the magazine: \nThe content comes from the results of different international polls, assembled over the course of a specific time period. The results are presented to the reader with easy to read graphics and enable readers to understand what people, as consumers and members of society, think on a global scale.  \u201cRevealing the world\u2019s opinion\u201d is our motto; your opinion is what makes Magic Numbers.\n\nAbout subscriptions: \nBesides the current issue of Magic Numbers Magazine, we offer our users the option to subscribe to the magazine with a great advantage! The subscription periods that we offer are for 3 or 6 months. Because Magic Numbers is a monthly digital magazine, our subscribers will have access to 3 or 6 issues of the magazine respectively, including the current issue. The subscription price is shown in the process of subscription and normally includes a discount of 20% to 30% over the regular single issue purchase. The subscriptions are auto-renewable; if you want to cancel your subscription, you must turn off the auto-renew in your account settings at least 24-hours prior to the end of the current period. \n- 3 Months subscription (3 issues): $11,99 US / 7,99 \u00a3 / 9,99 \u20ac\n- 6 Months Subscription (6 issues): $20,99 US / 14,99 \u00a3 / 16,99 \u20ac\n\nPlease visit our privacy policy and terms of use if you have any doubts: http://www.magicnumbers-mag.com/privacy-policy.html", "artistName": "Appgeneration Software", "artworkUrl512": "http://a1153.phobos.apple.com/us/r30/Purple/v4/7f/ea/f2/7feaf2a2-57b3-7b61-7bc7-e7a973a768e2/mzl.pymhidvf.png", "version": "1.7.1", "primaryGenreId": 6000, "primaryGenreName": "Business", "fileSizeBytes": "5910795", "price": 0.0, "isGameCenterEnabled": false, "trackCensoredName": "Magic Numbers Magazine", "genreIds": ["6000", "6021", "13025"], "trackName": "Magic Numbers Magazine", "releaseNotes": "Minor bug fixes.", "sellerUrl": "http://www.magicnumbers-mag.com", "screenshotUrls": ["http://a4.mzstatic.com/us/r30/Purple/v4/56/de/53/56de537f-eadc-b59f-890f-1d91a49b16e9/screen320x480.jpeg", "http://a2.mzstatic.com/us/r30/Purple/v4/51/c1/ce/51c1ced8-7093-7e21-b4dc-06be14e3f455/screen320x480.jpeg", "http://a4.mzstatic.com/us/r30/Purple/v4/0c/c9/23/0cc92300-6f59-df1f-2fe0-fcf4e8a36d21/screen320x480.jpeg", "http://a2.mzstatic.com/us/r30/Purple/v4/48/18/51/4818510f-6cf0-4bfb-7c51-cdd87254837c/screen320x480.jpeg", "http://a3.mzstatic.com/us/r30/Purple/v4/2f/90/b7/2f90b756-b7c6-f28f-cba4-4f226b5bff0a/screen320x480.jpeg"], "userRatingCount": 283, "trackContentRating": "4+", "formattedPrice": "Free", "artistViewUrl": "https://itunes.apple.com/us/artist/appgeneration-software/id386316599?uo=4", "kind": "software", "averageUserRatingForCurrentVersion": 3.0, "sellerName": "Appgeneration, Software Technologies, Lda", "supportedDevices": ["iPodTouchourthGen", "iPadMini", "iPad2Wifi", "iPhone5", "iPad3G", "iPhone-3GS", "iPhone4", "iPadThirdGen4G", "iPadThirdGen", "iPhone4S", "iPodTouchThirdGen", "iPadWifi", "iPadFourthGen", "iPadMini4G", "iPadFourthGen4G", "iPodTouchFifthGen", "iPhone5c", "iPad23G", "iPhone5s"], "artworkUrl100": "http://a1153.phobos.apple.com/us/r30/Purple/v4/7f/ea/f2/7feaf2a2-57b3-7b61-7bc7-e7a973a768e2/mzl.pymhidvf.png", "bundleId": "com.appgeneration.magicnumbers", "trackViewUrl": "https://itunes.apple.com/us/app/magic-numbers-magazine/id464805176?mt=8&uo=4", "minimumOsVersion": "5.0", "artworkUrl60": "http://a1439.phobos.apple.com/us/r30/Purple/v4/1d/1b/5a/1d1b5a6b-5740-0de7-8999-548a0414245d/Icon.png", "averageUserRating": 3.5}