{"contentAdvisoryRating": "12+", "features": ["gameCenter"], "languageCodesISO2A": ["EN"], "ipadScreenshotUrls": [], "releaseDate": "2012-05-17T23:27:06Z", "currency": "USD", "artistId": 306939927, "userRatingCountForCurrentVersion": 993, "wrapperType": "software", "advisories": ["Infrequent/Mild Realistic Violence", "Infrequent/Mild Horror/Fear Themes", "Frequent/Intense Cartoon or Fantasy Violence"], "genres": ["Games", "Entertainment", "Arcade", "Racing"], "trackId": 513670129, "description": "The creators of Doodle Army\u2122 Present \n\nZOMBIE ROAD RAGE\u2122 \n\nGet ready for the wildest ride across Undeath Valley! You are Roy Rage a truck drivin' redneck ready to take on the Zombie Apocalypse. Battle herds of flesh hungry zombies on your journey to score the best weaponry and gear that loot can buy. \n\nYou already know shooting zombies is fun, but now you can try it at 60mph! Dispose of the Zombie infestation any way you can. Take aim and use them as target practice, roll them over like speed bumps or turn them into bloody hood ornaments. Slay zombies to earn lot and buy cool new weapons. Then go the distance and beat your friends on the Game Center leader boards! \n\nHOW TO PLAY: \nUse your finger or thumb on the left side to guide the truck. Press the right side to fire your weapon. Collect Gas and Wrenches to continue on your journey shoot anything that moves or screams BRAINS!!!!! \n\nFEATURES: \n- 7 Un-lockable Weapons \n- Endless Re-playability \n- Game Center Score Tracking \n- 3 Control Styles \n- A \"No Blood\" option to satisfy that little girl in all of us. \n\nJust check out these player reviews... \n\n\"Would even make a hillbilly squeal like a piggy!\" \n\n\"Only zombies would enjoy the mindlessness of this game!\" \n\nCheck out our other great games: \nDoodle Army \nDoodle Army 2 \nFlip the Bird \nCannon Siege \nPocket Kite \nJonah & the Whale", "artistName": "Chad Towns", "artworkUrl512": "http://a142.phobos.apple.com/us/r30/Purple/v4/c5/18/6c/c5186ca5-7a55-5ee5-e91d-133555794d4c/mza_3863447399771545889.png", "version": "1.1.0", "primaryGenreId": 6014, "primaryGenreName": "Games", "fileSizeBytes": "10036219", "price": 0.0, "isGameCenterEnabled": true, "trackCensoredName": "Zombie Road Rage", "genreIds": ["6014", "6016", "7003", "7013"], "trackName": "Zombie Road Rage", "releaseNotes": "Added pause button.\nFixed firing bug.", "sellerUrl": "http://www.appsomniacs.com", "screenshotUrls": ["http://a3.mzstatic.com/us/r30/Purple/v4/af/c3/1a/afc31a41-3e4b-9603-45a9-98b5c06c06ed/screen320x480.jpeg", "http://a4.mzstatic.com/us/r30/Purple/v4/32/11/3d/32113d79-afe3-dbf9-d2a8-4a5754b9a470/screen320x480.jpeg", "http://a3.mzstatic.com/us/r30/Purple/v4/c1/e4/40/c1e44016-0acc-f52e-ca82-c94a15c4194f/screen320x480.jpeg", "http://a3.mzstatic.com/us/r30/Purple/v4/cf/c6/75/cfc67551-4d82-4593-58cb-f44598e26f7d/screen320x480.jpeg", "http://a4.mzstatic.com/us/r30/Purple/v4/43/a7/81/43a78149-270f-d2b6-792d-1329bc43e498/screen320x480.jpeg"], "userRatingCount": 1002, "trackContentRating": "12+", "formattedPrice": "Free", "artistViewUrl": "https://itunes.apple.com/us/artist/chad-towns/id306939927?uo=4", "kind": "software", "averageUserRatingForCurrentVersion": 3.5, "sellerName": "Chad Towns", "supportedDevices": ["iPadThirdGen4G", "iPhone5s", "iPhone", "iPhone5c", "iPadFourthGen", "iPadFourthGen4G", "iPodTouchourthGen", "iPad23G", "iPadWifi", "iPod-touch-with-mic", "iPodTouchThirdGen", "iPad2Wifi", "iPadMini4G", "iPadThirdGen", "iPhone5", "iPhone4", "iPhone-3G", "iPhone-3GS", "iPhone4S", "iPodTouchFifthGen", "iPadMini", "iPad3G", "iPod-touch"], "artworkUrl100": "http://a142.phobos.apple.com/us/r30/Purple/v4/c5/18/6c/c5186ca5-7a55-5ee5-e91d-133555794d4c/mza_3863447399771545889.png", "bundleId": "com.chadtowns.fingermobile", "trackViewUrl": "https://itunes.apple.com/us/app/zombie-road-rage/id513670129?mt=8&uo=4", "minimumOsVersion": "3.0", "artworkUrl60": "http://a836.phobos.apple.com/us/r30/Purple/v4/fa/5e/9e/fa5e9e38-12d0-d9fd-b641-74fde2eeab30/Icon.png", "averageUserRating": 3.5}